Metadata-Version: 2.1
Name: semantic_text_search_word_disambiguation
Version: 0.1.1
Summary: A package to create a semantic search word disambiguation functionality with vector db, NER, POS, Lemmatization support
Author: Sastry K V S R
Author-email: sivaram.kavuri@gmail.com
Classifier: Programming Language :: Python :: 3
Classifier: License :: OSI Approved :: MIT License
Classifier: Operating System :: OS Independent
Requires-Python: >=3.6
